pika_rabbitmq.py
Flask_PikaMQ-1.0.dist-info/LICENSE
Flask_PikaMQ-1.0.dist-info/METADATA
Flask_PikaMQ-1.0.dist-info/WHEEL
Flask_PikaMQ-1.0.dist-info/top_level.txt
Flask_PikaMQ-1.0.dist-info/RECORD
