Metadata-Version: 2.1
Name: Flask-PikaMQ
Version: 1.0
Summary: This is Extension for RabbitMQ Microservice
Home-page: 
Author: Rasco Developers
Author-email: rezahartono.rasco@gmail.com
License: BSD
Platform: any
Classifier: Environment :: Web Environment
Classifier: Intended Audience :: Developers
Classifier: License :: OSI Approved :: BSD License
Classifier: Operating System :: OS Independent
Classifier: Programming Language :: Python
Classifier: Topic :: Internet :: WWW/HTTP :: Dynamic Content
Classifier: Topic :: Software Development :: Libraries :: Python Modules
License-File: LICENSE
Requires-Dist: Flask
Requires-Dist: pika
